atudomain/__init__.py
atudomain/git/__init__.py
atudomain/git/objects.py
atudomain/git/parsers.py
atudomain/git/repository.py
tests/__init__.py
tests/test_Git.py
tests/test_GitBranchParser.py
tests/test_GitLogParser.py
tests/util.py
tests/resources/test_GitBranchParser/test_extract_branch_strings_1.txt
tests/resources/test_GitBranchParser/test_extract_branches_1.txt
tests/resources/test_GitLogParser/test_extract_commits_1.txt
atudomain_git-4.0.0.dist-info/LICENSE
atudomain_git-4.0.0.dist-info/METADATA
atudomain_git-4.0.0.dist-info/WHEEL
atudomain_git-4.0.0.dist-info/top_level.txt
atudomain_git-4.0.0.dist-info/RECORD
