Metadata-Version: 2.1
Name: atudomain-git
Version: 4.0.0
Summary: Convenience library for working with Git on Linux.
Home-page: https://github.com/atudomain/atudomain-git
Author: Adrian Tuzimek
Author-email: tuziomek@gmail.com
License: UNKNOWN
Keywords: api,git
Platform: UNKNOWN
Classifier: Programming Language :: Python :: 3 :: Only
Classifier: License :: OSI Approved :: BSD License
Classifier: Environment :: Console
Classifier: Intended Audience :: Developers
Classifier: Intended Audience :: System Administrators
Classifier: Intended Audience :: Information Technology
